LICENSE
MANIFEST.in
README.md
setup.cfg
setup.py
gitrisky/__init__.py
gitrisky/cli.py
gitrisky/gitcmds.py
gitrisky/model.py
gitrisky/parsing.py
gitrisky.egg-info/PKG-INFO
gitrisky.egg-info/SOURCES.txt
gitrisky.egg-info/dependency_links.txt
gitrisky.egg-info/entry_points.txt
gitrisky.egg-info/requires.txt
gitrisky.egg-info/top_level.txt
gitrisky/tests/__init__.py
gitrisky/tests/test_cli.py
gitrisky/tests/test_gitcmds.py
gitrisky/tests/test_model.py
gitrisky/tests/test_parsing.py