Metadata-Version: 1.1
Name: gitrisky
Version: 0.1.3
Summary: Predict code bug risk with git metadata
Home-page: https://github.com/hinnefe2/gitrisky
Author: J. Henry Hinnefeld
Author-email: henry.hinnefeld@gmail.com
License: UNKNOWN
Download-URL: https://github.com/hinnefe2/gitrisky/archive/0.1.3.tar.gz
Platform: UNKNOWN
Classifier: Programming Language :: Python
Classifier: Programming Language :: Python :: 3.5
Classifier: Programming Language :: Python :: 3.6
Classifier: Topic :: Software Development :: Version Control :: Git
Classifier: License :: OSI Approved :: MIT License
Classifier: Natural Language :: English
